fable/__init__.py
fable/core.py
fable/generators.py
fable/models.py
fabledata-0.0.2.dist-info/LICENSE
fabledata-0.0.2.dist-info/METADATA
fabledata-0.0.2.dist-info/WHEEL
fabledata-0.0.2.dist-info/top_level.txt
fabledata-0.0.2.dist-info/RECORD
