Metadata-Version: 2.1
Name: fabledata
Version: 0.0.2
Summary: README.md
Author-email: Jack Bonatakis <jackbonataki@gmail.com>
License-File: LICENSE
Requires-Dist: faker
Requires-Dist: polars
Requires-Dist: pydantic
Provides-Extra: dev
Requires-Dist: python-dotenv ; extra == 'dev'
Requires-Dist: pytest ; extra == 'dev'
Requires-Dist: ruff ; extra == 'dev'
